{"id":"8b7a9a57-2303-4ef5-9fc2-bf41713bd1fc","revision":0,"last_node_id":408,"last_link_id":675,"nodes":[{"id":138,"type":"WanVideoLoraSelect","pos":[508.0423040159985,-2806.5853012594516],"size":[511.52830744019707,155.41397253825608],"flags":{},"order":0,"mode":0,"inputs":[{"localized_name":"prev_lora","name":"prev_lora","shape":7,"type":"WANVIDLORA","link":null},{"localized_name":"blocks","name":"blocks","shape":7,"type":"SELECTEDBLOCKS","link":null},{"localized_name":"lora","name":"lora","type":"COMBO","widget":{"name":"lora"},"link":null},{"localized_name":"strength","name":"strength","type":"FLOAT","widget":{"name":"strength"},"link":null},{"localized_name":"low_mem_load","name":"low_mem_load","shape":7,"type":"BOOLEAN","widget":{"name":"low_mem_load"},"link":null},{"localized_name":"merge_loras","name":"merge_loras","shape":7,"type":"BOOLEAN","widget":{"name":"merge_loras"},"link":null}],"outputs":[{"localized_name":"lora","name":"lora","type":"WANVIDLORA","links":[349]}],"properties":{"cnr_id":"ComfyUI-WanVideoWrapper","ver":"058286fc0f3b0651a2f6b68309df3f06e8332cc0","Node name for S&R":"WanVideoLoraSelect","ue_properties":{"widget_ue_connectable":{},"version":"7.1","input_ue_unconnectable":{}}},"widgets_values":["lightx2v_I2V_14B_480p_cfg_step_distill_rank64_bf16.safetensors",1,false,false],"color":"#223","bgcolor":"#335"},{"id":120,"type":"MultiTalkModelLoader","pos":[506.11227923164853,-2590.5168969035794],"size":[511.7737121582031,66.51400756835938],"flags":{},"order":1,"mode":0,"inputs":[{"localized_name":"model","name":"model","type":"COMBO","widget":{"name":"model"},"link":null}],"outputs":[{"localized_name":"model","name":"model","type":"MULTITALKMODEL","links":[355]}],"properties":{"cnr_id":"ComfyUI-WanVideoWrapper","ver":"058286fc0f3b0651a2f6b68309df3f06e8332cc0","Node name for S&R":"MultiTalkModelLoader","ue_properties":{"widget_ue_connectable":{},"version":"7.1","input_ue_unconnectable":{}}},"widgets_values":["Wan2_1-InfiniteTalk_Single_Q8.gguf"],"color":"#223","bgcolor":"#335"},{"id":177,"type":"WanVideoTorchCompileSettings","pos":[512.4378977888026,-2311.9660605087915],"size":[507.87225616681826,227.3534931345639],"flags":{},"order":2,"mode":0,"inputs":[{"localized_name":"backend","name":"backend","type":"COMBO","widget":{"name":"backend"},"link":null},{"localized_name":"fullgraph","name":"fullgraph","type":"BOOLEAN","widget":{"name":"fullgraph"},"link":null},{"localized_name":"mode","name":"mode","type":"COMBO","widget":{"name":"mode"},"link":null},{"localized_name":"dynamic","name":"dynamic","type":"BOOLEAN","widget":{"name":"dynamic"},"link":null},{"localized_name":"dynamo_cache_size_limit","name":"dynamo_cache_size_limit","type":"INT","widget":{"name":"dynamo_cache_size_limit"},"link":null},{"localized_name":"compile_transformer_blocks_only","name":"compile_transformer_blocks_only","type":"BOOLEAN","widget":{"name":"compile_transformer_blocks_only"},"link":null},{"localized_name":"dynamo_recompile_limit","name":"dynamo_recompile_limit","shape":7,"type":"INT","widget":{"name":"dynamo_recompile_limit"},"link":null},{"localized_name":"force_parameter_static_shapes","name":"force_parameter_static_shapes","shape":7,"type":"BOOLEAN","widget":{"name":"force_parameter_static_shapes"},"link":null}],"outputs":[{"localized_name":"torch_compile_args","name":"torch_compile_args","type":"WANCOMPILEARGS","links":[]}],"properties":{"cnr_id":"ComfyUI-WanVideoWrapper","ver":"f3614e6720744247f3211d60f7b9333f43572384","Node name for S&R":"WanVideoTorchCompileSettings","ue_properties":{"widget_ue_connectable":{},"version":"7.1","input_ue_unconnectable":{}}},"widgets_values":["inductor",false,"default",false,64,true,128,false],"color":"#223","bgcolor":"#335"},{"id":134,"type":"WanVideoBlockSwap","pos":[503.9717070005554,-3067.5329849829477],"size":[516.9121022891509,202],"flags":{},"order":3,"mode":0,"inputs":[{"localized_name":"blocks_to_swap","name":"blocks_to_swap","type":"INT","widget":{"name":"blocks_to_swap"},"link":null},{"localized_name":"offload_img_emb","name":"offload_img_emb","type":"BOOLEAN","widget":{"name":"offload_img_emb"},"link":null},{"localized_name":"offload_txt_emb","name":"offload_txt_emb","type":"BOOLEAN","widget":{"name":"offload_txt_emb"},"link":null},{"localized_name":"use_non_blocking","name":"use_non_blocking","shape":7,"type":"BOOLEAN","widget":{"name":"use_non_blocking"},"link":null},{"localized_name":"vace_blocks_to_swap","name":"vace_blocks_to_swap","shape":7,"type":"INT","widget":{"name":"vace_blocks_to_swap"},"link":null},{"localized_name":"prefetch_blocks","name":"prefetch_blocks","shape":7,"type":"INT","widget":{"name":"prefetch_blocks"},"link":null},{"localized_name":"block_swap_debug","name":"block_swap_debug","shape":7,"type":"BOOLEAN","widget":{"name":"block_swap_debug"},"link":null}],"outputs":[{"localized_name":"block_swap_args","name":"block_swap_args","type":"BLOCKSWAPARGS","links":[362]}],"properties":{"cnr_id":"ComfyUI-WanVideoWrapper","ver":"058286fc0f3b0651a2f6b68309df3f06e8332cc0","Node name for S&R":"WanVideoBlockSwap","ue_properties":{"widget_ue_connectable":{},"version":"7.1","input_ue_unconnectable":{}}},"widgets_values":[20,false,false,true,0,1,false],"color":"#223","bgcolor":"#335"},{"id":238,"type":"CLIPVisionLoader","pos":[516.4786415737985,-2467.192260851777],"size":[498.74033974133044,58],"flags":{"collapsed":false},"order":4,"mode":0,"inputs":[{"localized_name":"clip_name","name":"clip_name","type":"COMBO","widget":{"name":"clip_name"},"link":null}],"outputs":[{"localized_name":"CLIP_VISION","name":"CLIP_VISION","type":"CLIP_VISION","links":[466]}],"properties":{"cnr_id":"comfy-core","ver":"0.3.50","Node name for S&R":"CLIPVisionLoader","ue_properties":{"widget_ue_connectable":{},"version":"7.1","input_ue_unconnectable":{}}},"widgets_values":["clip_vision_h.safetensors"],"color":"#233","bgcolor":"#355"},{"id":264,"type":"SetNode","pos":[833.9072721676869,-2372.100701897814],"size":[210,60],"flags":{"collapsed":true},"order":33,"mode":0,"inputs":[{"name":"CLIP_VISION","type":"CLIP_VISION","link":466}],"outputs":[{"name":"*","type":"*","links":null}],"title":"Set_clip_vision_model","properties":{"previousName":"clip_vision_model","ue_properties":{"widget_ue_connectable":{},"version":"7.1","input_ue_unconnectable":{}}},"widgets_values":["clip_vision_model"],"color":"#233","bgcolor":"#355"},{"id":129,"type":"WanVideoVAELoader","pos":[1046.1284574519225,-2206.986709518273],"size":[465.23773793661326,83.3534931345639],"flags":{},"order":5,"mode":0,"inputs":[{"localized_name":"compile_args","name":"compile_args","shape":7,"type":"WANCOMPILEARGS","link":null},{"localized_name":"model_name","name":"model_name","type":"COMBO","widget":{"name":"model_name"},"link":null},{"localized_name":"precision","name":"precision","shape":7,"type":"COMBO","widget":{"name":"precision"},"link":null}],"outputs":[{"localized_name":"vae","name":"vae","type":"WANVAE","slot_index":0,"links":[436]}],"properties":{"cnr_id":"ComfyUI-WanVideoWrapper","ver":"c3ee35f3ece76e38099dc516182d69b406e16772","Node name for S&R":"WanVideoVAELoader","ue_properties":{"widget_ue_connectable":{},"version":"7.1","input_ue_unconnectable":{}}},"widgets_values":["Wan2_1_VAE_bf16.safetensors","bf16"],"color":"#322","bgcolor":"#533"},{"id":240,"type":"SetNode","pos":[1407.881112314301,-2088.9651904676357],"size":[210,58],"flags":{"collapsed":true},"order":34,"mode":0,"inputs":[{"name":"WANVAE","type":"WANVAE","link":436}],"outputs":[{"name":"*","type":"*","links":null}],"title":"Set_VAE","properties":{"previousName":"VAE","ue_properties":{"widget_ue_connectable":{},"version":"7.1","input_ue_unconnectable":{}}},"widgets_values":["VAE"],"color":"#322","bgcolor":"#533"},{"id":122,"type":"WanVideoModelLoader","pos":[1113.3476691223027,-2846.9830030834073],"size":[668.1777954101562,338],"flags":{},"order":32,"mode":0,"inputs":[{"localized_name":"compile_args","name":"compile_args","shape":7,"type":"WANCOMPILEARGS","link":null},{"localized_name":"block_swap_args","name":"block_swap_args","shape":7,"type":"BLOCKSWAPARGS","link":362},{"localized_name":"lora","name":"lora","shape":7,"type":"WANVIDLORA","link":349},{"localized_name":"vram_management_args","name":"vram_management_args","shape":7,"type":"VRAM_MANAGEMENTARGS","link":null},{"localized_name":"extra_model","name":"extra_model","shape":7,"type":"VACEPATH","link":null},{"localized_name":"fantasytalking_model","name":"fantasytalking_model","shape":7,"type":"FANTASYTALKINGMODEL","link":null},{"localized_name":"multitalk_model","name":"multitalk_model","shape":7,"type":"MULTITALKMODEL","link":355},{"localized_name":"fantasyportrait_model","name":"fantasyportrait_model","shape":7,"type":"FANTASYPORTRAITMODEL","link":null},{"localized_name":"model","name":"model","type":"COMBO","widget":{"name":"model"},"link":null},{"localized_name":"base_precision","name":"base_precision","type":"COMBO","widget":{"name":"base_precision"},"link":null},{"localized_name":"quantization","name":"quantization","type":"COMBO","widget":{"name":"quantization"},"link":null},{"localized_name":"load_device","name":"load_device","type":"COMBO","widget":{"name":"load_device"},"link":null},{"localized_name":"attention_mode","name":"attention_mode","shape":7,"type":"COMBO","widget":{"name":"attention_mode"},"link":null},{"localized_name":"rms_norm_function","name":"rms_norm_function","shape":7,"type":"COMBO","widget":{"name":"rms_norm_function"},"link":null},{"name":"vace_model","shape":7,"type":"VACEPATH","link":null}],"outputs":[{"localized_name":"model","name":"model","type":"WANVIDEOMODEL","links":[463]}],"properties":{"cnr_id":"ComfyUI-WanVideoWrapper","ver":"058286fc0f3b0651a2f6b68309df3f06e8332cc0","Node name for S&R":"WanVideoModelLoader","ue_properties":{"widget_ue_connectable":{},"version":"7.1","input_ue_unconnectable":{}}},"widgets_values":["wan2.1-i2v-14b-720p-Q8_0.gguf","fp16_fast","disabled","offload_device","sageattn","default"],"color":"#223","bgcolor":"#335"},{"id":260,"type":"SetNode","pos":[1642.7385562466047,-2463.7850514263914],"size":[210,60],"flags":{"collapsed":true},"order":46,"mode":0,"inputs":[{"name":"WANVIDEOMODEL","type":"WANVIDEOMODEL","link":463}],"outputs":[{"name":"*","type":"*","links":null}],"title":"Set_wanmodel","properties":{"previousName":"wanmodel","ue_properties":{"widget_ue_connectable":{},"version":"7.1","input_ue_unconnectable":{}}},"widgets_values":["wanmodel"],"color":"#223","bgcolor":"#335"},{"id":346,"type":"SetNode","pos":[2382.3094064630186,-2346.551511560515],"size":[210,50],"flags":{"collapsed":true},"order":39,"mode":0,"inputs":[{"name":"STRING","type":"STRING","link":600}],"outputs":[{"name":"*","type":"*","links":null}],"title":"Set_positive_prompt","properties":{"previousName":"positive_prompt","ue_properties":{"widget_ue_connectable":{},"version":"7.1","input_ue_unconnectable":{}}},"widgets_values":["positive_prompt"],"color":"#232","bgcolor":"#353"},{"id":348,"type":"SetNode","pos":[2970.984893645929,-2346.734432384574],"size":[210,50],"flags":{"collapsed":true},"order":40,"mode":0,"inputs":[{"name":"STRING","type":"STRING","link":599}],"outputs":[{"name":"*","type":"*","links":null}],"title":"Set_negative_prompt","properties":{"previousName":"negative_prompt","ue_properties":{"widget_ue_connectable":{},"version":"7.1","input_ue_unconnectable":{}}},"widgets_values":["negative_prompt"],"color":"#322","bgcolor":"#533"},{"id":245,"type":"INTConstant","pos":[1990.1701550198306,-2294.8316255300074],"size":[383.98747847193,58],"flags":{},"order":6,"mode":0,"inputs":[{"localized_name":"value","name":"value","type":"INT","widget":{"name":"value"},"link":null}],"outputs":[{"localized_name":"value","name":"value","type":"INT","links":[441]}],"title":"Width","properties":{"cnr_id":"comfyui-kjnodes","ver":"e435e999e4b1a828a6b5f6d8f037e66f4a798324","Node name for S&R":"INTConstant","ue_properties":{"widget_ue_connectable":{},"version":"7.1","input_ue_unconnectable":{}}},"widgets_values":[690],"color":"#1b4669","bgcolor":"#29699c"},{"id":246,"type":"INTConstant","pos":[2395.3866465712103,-2294.8015062244094],"size":[383.98747847193,58],"flags":{},"order":7,"mode":0,"inputs":[{"localized_name":"value","name":"value","type":"INT","widget":{"name":"value"},"link":null}],"outputs":[{"localized_name":"value","name":"value","type":"INT","links":[442]}],"title":"Height","properties":{"cnr_id":"comfyui-kjnodes","ver":"e435e999e4b1a828a6b5f6d8f037e66f4a798324","Node name for S&R":"INTConstant","ue_properties":{"widget_ue_connectable":{},"version":"7.1","input_ue_unconnectable":{}}},"widgets_values":[920],"color":"#1b4669","bgcolor":"#29699c"},{"id":270,"type":"INTConstant","pos":[2799.742230027211,-2292.648687880341],"size":[355.96264972477366,58],"flags":{},"order":8,"mode":0,"inputs":[{"localized_name":"value","name":"value","type":"INT","widget":{"name":"value"},"link":null}],"outputs":[{"localized_name":"value","name":"value","type":"INT","links":[472]}],"title":"Max frames","properties":{"cnr_id":"comfyui-kjnodes","ver":"e435e999e4b1a828a6b5f6d8f037e66f4a798324","Node name for S&R":"INTConstant","ue_properties":{"widget_ue_connectable":{},"version":"7.1","input_ue_unconnectable":{}}},"widgets_values":[500],"color":"#1b4669","bgcolor":"#29699c"},{"id":248,"type":"SetNode","pos":[2661.40737887742,-2199.255603069851],"size":[210,58],"flags":{"collapsed":true},"order":36,"mode":0,"inputs":[{"name":"INT","type":"INT","link":442}],"outputs":[{"name":"*","type":"*","links":null}],"title":"Set_height","properties":{"previousName":"height","ue_properties":{"widget_ue_connectable":{},"version":"7.1","input_ue_unconnectable":{}}},"widgets_values":["height"],"color":"#1b4669","bgcolor":"#29699c"},{"id":247,"type":"SetNode","pos":[2260.6241237818303,-2200.1484788827156],"size":[210,60],"flags":{"collapsed":true},"order":35,"mode":0,"inputs":[{"name":"INT","type":"INT","link":441}],"outputs":[{"name":"*","type":"*","links":null}],"title":"Set_width","properties":{"previousName":"width","ue_properties":{"widget_ue_connectable":{},"version":"7.1","input_ue_unconnectable":{}}},"widgets_values":["width"],"color":"#1b4669","bgcolor":"#29699c"},{"id":365,"type":"PreviewImage","pos":[526.4928555861574,-1806.23657831166],"size":[327.8399508556698,246],"flags":{},"order":48,"mode":0,"inputs":[{"localized_name":"images","name":"images","type":"IMAGE","link":603}],"outputs":[],"properties":{"cnr_id":"comfy-core","ver":"0.3.67","Node name for S&R":"PreviewImage"},"widgets_values":[],"color":"#223","bgcolor":"#335"},{"id":283,"type":"GetNode","pos":[879.7781484217145,-1932.955732064485],"size":[210,34],"flags":{"collapsed":true},"order":9,"mode":0,"inputs":[],"outputs":[{"name":"INT","type":"INT","links":[494]}],"title":"Get_width","properties":{"ue_properties":{"widget_ue_connectable":{},"version":"7.1","input_ue_unconnectable":{}}},"widgets_values":["width"],"color":"#223","bgcolor":"#335"},{"id":291,"type":"GetImageSizeAndCount","pos":[1186.6313214746322,-1893.931197044454],"size":[190.86484375,86],"flags":{"collapsed":false},"order":54,"mode":0,"inputs":[{"localized_name":"image","name":"image","type":"IMAGE","link":538}],"outputs":[{"localized_name":"image","name":"image","type":"IMAGE","links":[539,540]},{"label":"688 width","localized_name":"width","name":"width","type":"INT","links":[516]},{"label":"912 height","localized_name":"height","name":"height","type":"INT","links":[517]},{"label":"1 count","localized_name":"count","name":"count","type":"INT","links":null}],"properties":{"cnr_id":"comfyui-kjnodes","ver":"6dfd2c2420260dbb321a3412b9f1dff439a0f2e3","Node name for S&R":"GetImageSizeAndCount","ue_properties":{"widget_ue_connectable":{},"version":"7.1","input_ue_unconnectable":{}}},"widgets_values":[],"color":"#223","bgcolor":"#335"},{"id":265,"type":"GetNode","pos":[1407.4841842124765,-1931.6196832475853],"size":[210,60],"flags":{"collapsed":true},"order":10,"mode":0,"inputs":[],"outputs":[{"name":"CLIP_VISION","type":"CLIP_VISION","links":[467]}],"title":"Get_clip_vision_model","properties":{"ue_properties":{"widget_ue_connectable":{},"version":"7.1","input_ue_unconnectable":{}}},"widgets_values":["clip_vision_model"],"color":"#223","bgcolor":"#335"},{"id":237,"type":"WanVideoClipVisionEncode","pos":[1414.317377361239,-1890.149070835167],"size":[305.3647866873539,269.3162933060107],"flags":{},"order":56,"mode":0,"inputs":[{"localized_name":"clip_vision","name":"clip_vision","type":"CLIP_VISION","link":467},{"localized_name":"image_1","name":"image_1","type":"IMAGE","link":539},{"localized_name":"image_2","name":"image_2","shape":7,"type":"IMAGE","link":null},{"localized_name":"negative_image","name":"negative_image","shape":7,"type":"IMAGE","link":null},{"localized_name":"strength_1","name":"strength_1","type":"FLOAT","widget":{"name":"strength_1"},"link":null},{"localized_name":"strength_2","name":"strength_2","type":"FLOAT","widget":{"name":"strength_2"},"link":null},{"localized_name":"crop","name":"crop","type":"COMBO","widget":{"name":"crop"},"link":null},{"localized_name":"combine_embeds","name":"combine_embeds","type":"COMBO","widget":{"name":"combine_embeds"},"link":null},{"localized_name":"force_offload","name":"force_offload","type":"BOOLEAN","widget":{"name":"force_offload"},"link":null},{"localized_name":"tiles","name":"tiles","shape":7,"type":"INT","widget":{"name":"tiles"},"link":null},{"localized_name":"ratio","name":"ratio","shape":7,"type":"FLOAT","widget":{"name":"ratio"},"link":null}],"outputs":[{"localized_name":"image_embeds","name":"image_embeds","type":"WANVIDIMAGE_CLIPEMBEDS","links":[433]}],"properties":{"cnr_id":"ComfyUI-WanVideoWrapper","ver":"ff779c91714d8ee3484cd4119b082c72a1734b72","Node name for S&R":"WanVideoClipVisionEncode","ue_properties":{"widget_ue_connectable":{},"version":"7.1","input_ue_unconnectable":{}}},"widgets_values":[1,1,"center","average",true,0,0.5],"color":"#223","bgcolor":"#335"},{"id":282,"type":"GetNode","pos":[876.3750673612916,-1967.9740592082971],"size":[210,34],"flags":{"collapsed":true},"order":11,"mode":0,"inputs":[],"outputs":[{"name":"INT","type":"INT","links":[495]}],"title":"Get_height","properties":{"ue_properties":{"widget_ue_connectable":{},"version":"7.1","input_ue_unconnectable":{}}},"widgets_values":["height"],"color":"#223","bgcolor":"#335"},{"id":366,"type":"GetNode","pos":[2281.172995906381,-1976.885683319464],"size":[210,50],"flags":{"collapsed":true},"order":12,"mode":0,"inputs":[],"outputs":[{"name":"STRING","type":"STRING","links":[604]}],"title":"Get_positive_prompt","properties":{"ue_properties":{"widget_ue_connectable":{},"version":"7.1","input_ue_unconnectable":{}}},"widgets_values":["positive_prompt"],"color":"#232","bgcolor":"#353"},{"id":367,"type":"GetNode","pos":[2281.172995906375,-1938.4152657982036],"size":[210,58],"flags":{"collapsed":true},"order":13,"mode":0,"inputs":[],"outputs":[{"name":"STRING","type":"STRING","links":[605]}],"title":"Get_negative_prompt","properties":{"ue_properties":{"widget_ue_connectable":{},"version":"7.1","input_ue_unconnectable":{}}},"widgets_values":["negative_prompt"],"color":"#322","bgcolor":"#533"},{"id":244,"type":"GetNode","pos":[2287.330719450987,-1460.1373678713414],"size":[210,34],"flags":{"collapsed":true},"order":14,"mode":0,"inputs":[],"outputs":[{"name":"WANVAE","type":"WANVAE","links":[440]}],"title":"Get_VAE","properties":{"ue_properties":{"widget_ue_connectable":{},"version":"7.1","input_ue_unconnectable":{}}},"widgets_values":["VAE"],"color":"#432","bgcolor":"#653"},{"id":192,"type":"WanVideoImageToVideoMultiTalk","pos":[2286.078708166234,-1420.0876122041327],"size":[458.9615082479231,293.12456987851215],"flags":{},"order":59,"mode":0,"inputs":[{"localized_name":"vae","name":"vae","type":"WANVAE","link":440},{"localized_name":"start_image","name":"start_image","shape":7,"type":"IMAGE","link":540},{"localized_name":"clip_embeds","name":"clip_embeds","shape":7,"type":"WANVIDIMAGE_CLIPEMBEDS","link":433},{"localized_name":"width","name":"width","type":"INT","widget":{"name":"width"},"link":516},{"localized_name":"height","name":"height","type":"INT","widget":{"name":"height"},"link":517},{"localized_name":"frame_window_size","name":"frame_window_size","type":"INT","widget":{"name":"frame_window_size"},"link":null},{"localized_name":"motion_frame","name":"motion_frame","type":"INT","widget":{"name":"motion_frame"},"link":null},{"localized_name":"force_offload","name":"force_offload","type":"BOOLEAN","widget":{"name":"force_offload"},"link":null},{"localized_name":"colormatch","name":"colormatch","type":"COMBO","widget":{"name":"colormatch"},"link":null},{"localized_name":"tiled_vae","name":"tiled_vae","shape":7,"type":"BOOLEAN","widget":{"name":"tiled_vae"},"link":null},{"localized_name":"mode","name":"mode","shape":7,"type":"COMBO","widget":{"name":"mode"},"link":null},{"localized_name":"output_path","name":"output_path","shape":7,"type":"STRING","widget":{"name":"output_path"},"link":null}],"outputs":[{"localized_name":"image_embeds","name":"image_embeds","type":"WANVIDIMAGE_EMBEDS","links":[413]},{"localized_name":"output_path","name":"output_path","type":"STRING","links":[]}],"properties":{"cnr_id":"ComfyUI-WanVideoWrapper","ver":"49430f900bf812a1e281560bafafd04c43dfdf13","Node name for S&R":"WanVideoImageToVideoMultiTalk","ue_properties":{"widget_ue_connectable":{"width":true,"height":true},"version":"7.1","input_ue_unconnectable":{}}},"widgets_values":[832,480,81,9,false,"disabled",false,"infinitetalk",""],"color":"#332922","bgcolor":"#593930"},{"id":311,"type":"WanVideoTeaCache","pos":[2775.6991950744828,-1938.5858587907437],"size":[270,178],"flags":{"collapsed":true},"order":15,"mode":0,"inputs":[{"localized_name":"rel_l1_thresh","name":"rel_l1_thresh","type":"FLOAT","widget":{"name":"rel_l1_thresh"},"link":null},{"localized_name":"start_step","name":"start_step","type":"INT","widget":{"name":"start_step"},"link":null},{"localized_name":"end_step","name":"end_step","type":"INT","widget":{"name":"end_step"},"link":null},{"localized_name":"cache_device","name":"cache_device","type":"COMBO","widget":{"name":"cache_device"},"link":null},{"localized_name":"use_coefficients","name":"use_coefficients","type":"BOOLEAN","widget":{"name":"use_coefficients"},"link":null},{"localized_name":"mode","name":"mode","shape":7,"type":"COMBO","widget":{"name":"mode"},"link":null}],"outputs":[{"localized_name":"cache_args","name":"cache_args","type":"CACHEARGS","links":[552]}],"properties":{"cnr_id":"ComfyUI-WanVideoWrapper","ver":"3d42bf62cedf4f760edadba9e9c55869105d0bba","Node name for S&R":"WanVideoTeaCache"},"widgets_values":[0.3,1,-1,"offload_device",true,"e"],"color":"#332922","bgcolor":"#593930"},{"id":301,"type":"MelBandRoFormerModelLoader","pos":[549.9309451920327,-1107.2303860050067],"size":[400.5706481933594,58],"flags":{},"order":16,"mode":0,"inputs":[{"localized_name":"model_name","name":"model_name","type":"COMBO","widget":{"name":"model_name"},"link":null}],"outputs":[{"localized_name":"model","name":"model","type":"MELROFORMERMODEL","links":[543]}],"properties":{"cnr_id":"ComfyUI-MelBandRoFormer","ver":"b68d9077815387b64d596f8c39607052b95b6eba","Node name for S&R":"MelBandRoFormerModelLoader","ue_properties":{"widget_ue_connectable":{},"version":"7.1","input_ue_unconnectable":{}}},"widgets_values":["MelBandRoformer_fp16.safetensors"],"color":"#2a363b","bgcolor":"#3f5159"},{"id":300,"type":"Wav2VecModelLoader","pos":[557.3476327733915,-849.8488740055307],"size":[346.9834289550781,106],"flags":{},"order":17,"mode":4,"inputs":[{"localized_name":"model","name":"model","type":"COMBO","widget":{"name":"model"},"link":null},{"localized_name":"base_precision","name":"base_precision","type":"COMBO","widget":{"name":"base_precision"},"link":null},{"localized_name":"load_device","name":"load_device","type":"COMBO","widget":{"name":"load_device"},"link":null}],"outputs":[{"localized_name":"wav2vec_model","name":"wav2vec_model","type":"WAV2VECMODEL","links":null}],"properties":{"cnr_id":"ComfyUI-WanVideoWrapper","ver":"6fce0e2d3bb976b0006bc6d8e37e1f23460938ee","Node name for S&R":"Wav2VecModelLoader","ue_properties":{"widget_ue_connectable":{},"version":"7.1","input_ue_unconnectable":{}}},"widgets_values":["wav2vec2-chinese-base_fp16.safetensors","fp16","main_device"]},{"id":137,"type":"DownloadAndLoadWav2VecModel","pos":[554.4191931189396,-1003.8384782312443],"size":[396.9425505031526,106],"flags":{},"order":18,"mode":0,"inputs":[{"localized_name":"model","name":"model","type":"COMBO","widget":{"name":"model"},"link":null},{"localized_name":"base_precision","name":"base_precision","type":"COMBO","widget":{"name":"base_precision"},"link":null},{"localized_name":"load_device","name":"load_device","type":"COMBO","widget":{"name":"load_device"},"link":null}],"outputs":[{"localized_name":"wav2vec_model","name":"wav2vec_model","type":"WAV2VECMODEL","links":[334]}],"properties":{"cnr_id":"ComfyUI-WanVideoWrapper","ver":"058286fc0f3b0651a2f6b68309df3f06e8332cc0","Node name for S&R":"DownloadAndLoadWav2VecModel","ue_properties":{"widget_ue_connectable":{},"version":"7.1","input_ue_unconnectable":{}}},"widgets_values":["TencentGameMate/chinese-wav2vec2-base","fp16","main_device"],"color":"#2a363b","bgcolor":"#3f5159"},{"id":272,"type":"GetNode","pos":[1015.7595854355906,-1257.3718228668772],"size":[210,60],"flags":{"collapsed":true},"order":19,"mode":0,"inputs":[],"outputs":[{"name":"INT","type":"INT","links":[529]}],"title":"Get_max_frames","properties":{"ue_properties":{"widget_ue_connectable":{},"version":"7.1","input_ue_unconnectable":{}}},"widgets_values":["max_frames"],"color":"#1b4669","bgcolor":"#29699c"},{"id":294,"type":"SetNode","pos":[1014.2702780612917,-901.278925020554],"size":[210,60],"flags":{"collapsed":true},"order":58,"mode":0,"inputs":[{"name":"INT","type":"INT","link":519}],"outputs":[{"name":"*","type":"*","links":[]}],"title":"Set_actual_audio_frames","properties":{"previousName":"actual_audio_frames","ue_properties":{"widget_ue_connectable":{},"version":"7.1","input_ue_unconnectable":{}}},"widgets_values":["actual_audio_frames"],"color":"#1b4669","bgcolor":"#29699c"},{"id":261,"type":"GetNode","pos":[2772.4453506996683,-1974.221295960054],"size":[210,60],"flags":{"collapsed":true},"order":20,"mode":0,"inputs":[],"outputs":[{"name":"WANVIDEOMODEL","type":"WANVIDEOMODEL","links":[464]}],"title":"Get_wanmodel","properties":{"ue_properties":{"widget_ue_connectable":{},"version":"7.1","input_ue_unconnectable":{}}},"widgets_values":["wanmodel"],"color":"#223","bgcolor":"#335"},{"id":241,"type":"WanVideoTextEncodeCached","pos":[2282.2526614156327,-1895.1209461762728],"size":[465.5179138183594,386.354248046875],"flags":{},"order":38,"mode":0,"inputs":[{"localized_name":"extender_args","name":"extender_args","shape":7,"type":"WANVIDEOPROMPTEXTENDER_ARGS","link":null},{"localized_name":"model_name","name":"model_name","type":"COMBO","widget":{"name":"model_name"},"link":null},{"localized_name":"precision","name":"precision","type":"COMBO","widget":{"name":"precision"},"link":null},{"localized_name":"positive_prompt","name":"positive_prompt","type":"STRING","widget":{"name":"positive_prompt"},"link":604},{"localized_name":"negative_prompt","name":"negative_prompt","type":"STRING","widget":{"name":"negative_prompt"},"link":605},{"localized_name":"quantization","name":"quantization","type":"COMBO","widget":{"name":"quantization"},"link":null},{"localized_name":"use_disk_cache","name":"use_disk_cache","type":"BOOLEAN","widget":{"name":"use_disk_cache"},"link":null},{"localized_name":"device","name":"device","type":"COMBO","widget":{"name":"device"},"link":null}],"outputs":[{"localized_name":"text_embeds","name":"text_embeds","type":"WANVIDEOTEXTEMBEDS","links":[437]},{"localized_name":"negative_text_embeds","name":"negative_text_embeds","type":"WANVIDEOTEXTEMBEDS","links":null},{"localized_name":"positive_prompt","name":"positive_prompt","type":"STRING","links":null}],"properties":{"cnr_id":"ComfyUI-WanVideoWrapper","ver":"ff779c91714d8ee3484cd4119b082c72a1734b72","Node name for S&R":"WanVideoTextEncodeCached","ue_properties":{"widget_ue_connectable":{},"version":"7.1","input_ue_unconnectable":{}}},"widgets_values":["umt5-xxl-enc-bf16.safetensors","bf16","a woman is singing","bright tones, overexposed, static, blurred details, subtitles, style, works, paintings, images, static, overall gray, worst quality, low quality, JPEG compression residue, ugly, incomplete, extra fingers, poorly drawn hands, poorly drawn faces, deformed, disfigured, misshapen limbs, fused fingers, still picture, messy background, three legs, many people in the background, walking backwards","disabled",false,"gpu"],"color":"#332922","bgcolor":"#593930"},{"id":373,"type":"VHS_LoadAudio","pos":[552.9948500807403,-1355.997219658608],"size":[396.94844347405524,180],"flags":{},"order":42,"mode":0,"inputs":[{"localized_name":"audio_file","name":"audio_file","type":"STRING","widget":{"name":"audio_file"},"link":641},{"localized_name":"seek_seconds","name":"seek_seconds","shape":7,"type":"FLOAT","widget":{"name":"seek_seconds"},"link":null},{"localized_name":"duration","name":"duration","shape":7,"type":"FLOAT","widget":{"name":"duration"},"link":null}],"outputs":[{"localized_name":"audio","name":"audio","type":"AUDIO","links":[612,613]},{"localized_name":"duration","name":"duration","type":"FLOAT","links":null}],"properties":{"cnr_id":"comfyui-videohelpersuite","ver":"8550981384301e9bc5bfea83e5c2c75258102593","Node name for S&R":"VHS_LoadAudio"},"widgets_values":{"audio_file":"input/","seek_seconds":0,"duration":0,"audiopreview":{"params":{"start_time":0,"duration":0}}},"color":"#233","bgcolor":"#355"},{"id":302,"type":"MelBandRoFormerSampler","pos":[1013.3911726483188,-1349.5698052672412],"size":[293.48806939219173,46],"flags":{},"order":49,"mode":0,"inputs":[{"localized_name":"model","name":"model","type":"MELROFORMERMODEL","link":543},{"localized_name":"audio","name":"audio","type":"AUDIO","link":612}],"outputs":[{"localized_name":"vocals","name":"vocals","type":"AUDIO","links":[544]},{"localized_name":"instruments","name":"instruments","type":"AUDIO","links":null}],"properties":{"cnr_id":"ComfyUI-MelBandRoFormer","ver":"b68d9077815387b64d596f8c39607052b95b6eba","Node name for S&R":"MelBandRoFormerSampler","ue_properties":{"widget_ue_connectable":{},"version":"7.1","input_ue_unconnectable":{}}},"widgets_values":[],"color":"#2a363b","bgcolor":"#3f5159"},{"id":253,"type":"SetNode","pos":[1017.7870186799016,-1387.4505196240439],"size":[210,60],"flags":{"collapsed":true},"order":50,"mode":0,"inputs":[{"name":"AUDIO","type":"AUDIO","link":613}],"outputs":[{"name":"*","type":"*","links":[]}],"title":"Set_input_audio","properties":{"previousName":"input_audio","ue_properties":{"widget_ue_connectable":{},"version":"7.1","input_ue_unconnectable":{}}},"widgets_values":["input_audio"],"color":"#2a363b","bgcolor":"#3f5159"},{"id":361,"type":"blueeInput","pos":[1971.8371255468403,-2605.9965353227367],"size":[581.2427020416667,226.53367308698216],"flags":{},"order":21,"mode":0,"inputs":[{"localized_name":"text","name":"text","type":"STRING","widget":{"name":"text"},"link":null}],"outputs":[{"localized_name":"text","name":"text","type":"STRING","links":[600]}],"title":"PositivePrompt","properties":{"aux_id":"WenerSantos3/ComfyUI-bluee-utils","ver":"cf6192280ac09efacd375ee47155f40d5362692c","Node name for S&R":"blueeInput"},"widgets_values":["The person maintains a calm and confident posture, making slow movements and breathing calmly."],"color":"#232","bgcolor":"#353"},{"id":271,"type":"SetNode","pos":[3003.62875770483,-2199.5167890839066],"size":[210,50],"flags":{"collapsed":true},"order":37,"mode":0,"inputs":[{"name":"INT","type":"INT","link":472}],"outputs":[{"name":"*","type":"*","links":null}],"title":"Set_max_frames","properties":{"previousName":"max_frames","ue_properties":{"widget_ue_connectable":{},"version":"7.1","input_ue_unconnectable":{}}},"widgets_values":["max_frames"],"color":"#1b4669","bgcolor":"#29699c"},{"id":364,"type":"BlueeUtilsReadTempImage","pos":[526.4928555861579,-1904.3234789267092],"size":[325.178908903051,58],"flags":{},"order":41,"mode":0,"inputs":[{"localized_name":"path","name":"path","type":"STRING","widget":{"name":"path"},"link":639}],"outputs":[{"localized_name":"image","name":"image","type":"IMAGE","links":[602,603]}],"properties":{"aux_id":"WenerSantos3/ComfyUI-bluee-utils","ver":"cf6192280ac09efacd375ee47155f40d5362692c","Node name for S&R":"BlueeUtilsReadTempImage"},"widgets_values":[""],"color":"#223","bgcolor":"#335"},{"id":358,"type":"BlueeUtilsDownloadTemp","pos":[2302.2494191316773,-2948.5115334577545],"size":[279.644140625,106],"flags":{},"order":44,"mode":0,"inputs":[{"localized_name":"url","name":"url","type":"STRING","widget":{"name":"url"},"link":595},{"localized_name":"filename","name":"filename","shape":7,"type":"STRING","widget":{"name":"filename"},"link":null},{"localized_name":"path","name":"path","shape":7,"type":"STRING","widget":{"name":"path"},"link":null}],"outputs":[{"localized_name":"path","name":"path","type":"STRING","links":[596]}],"properties":{"aux_id":"WenerSantos3/ComfyUI-bluee-utils","ver":"cf6192280ac09efacd375ee47155f40d5362692c","Node name for S&R":"BlueeUtilsDownloadTemp"},"widgets_values":["","","/workspace/temp"]},{"id":355,"type":"BlueeUtilsDownloadTemp","pos":[2299.1728707061015,-3090.032761034239],"size":[279.644140625,106],"flags":{},"order":45,"mode":0,"inputs":[{"localized_name":"url","name":"url","type":"STRING","widget":{"name":"url"},"link":592},{"localized_name":"filename","name":"filename","shape":7,"type":"STRING","widget":{"name":"filename"},"link":null},{"localized_name":"path","name":"path","shape":7,"type":"STRING","widget":{"name":"path"},"link":null}],"outputs":[{"localized_name":"path","name":"path","type":"STRING","links":[593]}],"properties":{"aux_id":"WenerSantos3/ComfyUI-bluee-utils","ver":"cf6192280ac09efacd375ee47155f40d5362692c","Node name for S&R":"BlueeUtilsDownloadTemp"},"widgets_values":["","","/workspace/temp"]},{"id":362,"type":"blueeInput","pos":[2562.859280076844,-2606.2319491188423],"size":[584.8688060382337,226.76908688309095],"flags":{},"order":22,"mode":0,"inputs":[{"localized_name":"text","name":"text","type":"STRING","widget":{"name":"text"},"link":null}],"outputs":[{"localized_name":"text","name":"text","type":"STRING","links":[599]}],"title":"NegativePrompt","properties":{"aux_id":"WenerSantos3/ComfyUI-bluee-utils","ver":"cf6192280ac09efacd375ee47155f40d5362692c","Node name for S&R":"blueeInput"},"widgets_values":["色调过亮、曝光过度、静态、细节模糊、标题、风格、作品、绘画、图像、静态、整体灰暗、质量极差、低质量、JPEG压缩痕迹、丑陋、不完整、多余手指、手部绘制粗糙、面部绘制粗糙、变形、毁容、肢体畸形、手指畸形、手指融合、静态图像、杂乱背景、三条腿、背景中人物过多、倒退行走"],"color":"#322","bgcolor":"#533"},{"id":352,"type":"GetNode","pos":[529.8316441799564,-1946.0171871608627],"size":[210,58],"flags":{"collapsed":true},"order":23,"mode":0,"inputs":[],"outputs":[{"name":"STRING","type":"STRING","links":[639]}],"title":"Get_ImagePath","properties":{"ue_properties":{"widget_ue_connectable":{},"version":"7.1","input_ue_unconnectable":{}}},"widgets_values":["ImagePath"],"color":"#223","bgcolor":"#335"},{"id":369,"type":"GetNode","pos":[557.6596198591866,-1397.6466985677212],"size":[210,58],"flags":{"collapsed":true},"order":24,"mode":0,"inputs":[],"outputs":[{"name":"STRING","type":"STRING","links":[641]}],"title":"Get_AudioPath","properties":{"ue_properties":{"widget_ue_connectable":{},"version":"7.1","input_ue_unconnectable":{}}},"widgets_values":["AudioPath"],"color":"#2a363b","bgcolor":"#3f5159"},{"id":370,"type":"PreviewAudio","pos":[1341.7084575533074,-1158.44932358022],"size":[270,88],"flags":{},"order":57,"mode":0,"inputs":[{"localized_name":"audio","name":"audio","type":"AUDIO","link":609},{"localized_name":"audioUI","name":"audioUI","type":"AUDIO_UI","widget":{"name":"audioUI"},"link":null}],"outputs":[],"properties":{"cnr_id":"comfy-core","ver":"0.3.67","Node name for S&R":"PreviewAudio"},"widgets_values":[]},{"id":360,"type":"blueeInput","pos":[1968.672302915759,-2790.4583401455625],"size":[293.3463212467077,88],"flags":{},"order":25,"mode":0,"inputs":[{"localized_name":"text","name":"text","type":"STRING","widget":{"name":"text"},"link":null}],"outputs":[{"localized_name":"text","name":"text","type":"STRING","links":[598]}],"title":"setFileName","properties":{"aux_id":"WenerSantos3/ComfyUI-bluee-utils","ver":"cf6192280ac09efacd375ee47155f40d5362692c","Node name for S&R":"blueeInput"},"widgets_values":["{{uuid}}"],"color":"#233","bgcolor":"#355"},{"id":350,"type":"SetNode","pos":[2105.459049971928,-2666.2186060114145],"size":[263.7404497755888,89.45782425888137],"flags":{"collapsed":true},"order":43,"mode":0,"inputs":[{"name":"STRING","type":"STRING","link":598}],"outputs":[{"name":"STRING","type":"STRING","links":[587]}],"title":"Set_SetNameFile","properties":{"previousName":"SetNameFile","ue_properties":{"widget_ue_connectable":{},"version":"7.1","input_ue_unconnectable":{}}},"widgets_values":["SetNameFile"],"color":"#432","bgcolor":"#653"},{"id":339,"type":"SetNode","pos":[2595.743959065199,-3061.364822234086],"size":[210,58],"flags":{"collapsed":true},"order":53,"mode":0,"inputs":[{"name":"STRING","type":"STRING","link":593}],"outputs":[{"name":"*","type":"*","links":[]}],"title":"Set_ImagePath","properties":{"previousName":"ImagePath","ue_properties":{"widget_ue_connectable":{},"version":"7.1","input_ue_unconnectable":{}}},"widgets_values":["ImagePath"],"color":"#223","bgcolor":"#335"},{"id":342,"type":"SetNode","pos":[2595.395871257301,-2921.3466514154584],"size":[210,58],"flags":{"collapsed":true},"order":52,"mode":0,"inputs":[{"name":"STRING","type":"STRING","link":596}],"outputs":[{"name":"*","type":"*","links":[]}],"title":"Set_AudioPath","properties":{"previousName":"AudioPath","ue_properties":{"widget_ue_connectable":{},"version":"7.1","input_ue_unconnectable":{}}},"widgets_values":["AudioPath"],"color":"#223","bgcolor":"#335"},{"id":351,"type":"PreviewAny","pos":[2307.7271428258355,-2799.9657739821982],"size":[214.22554227108617,88],"flags":{},"order":51,"mode":0,"inputs":[{"localized_name":"source","name":"source","type":"*","link":587}],"outputs":[],"properties":{"cnr_id":"comfy-core","ver":"0.3.67","Node name for S&R":"PreviewAny"},"widgets_values":[]},{"id":309,"type":"WanVideoPassImagesFromSamples","pos":[3211.40948532848,-2981.085162932809],"size":[321.5958557128906,46],"flags":{},"order":61,"mode":0,"inputs":[{"localized_name":"samples","name":"samples","type":"LATENT","link":550}],"outputs":[{"localized_name":"images","name":"images","type":"IMAGE","links":[662]},{"localized_name":"output_path","name":"output_path","type":"STRING","links":[]}],"properties":{"cnr_id":"ComfyUI-WanVideoWrapper","ver":"e5955d83958f1c808c86e5be3804ca42b39ab3fa","Node name for S&R":"WanVideoPassImagesFromSamples","ue_properties":{"widget_ue_connectable":{},"version":"7.1","input_ue_unconnectable":{}}},"widgets_values":[],"color":"#2a363b","bgcolor":"#3f5159"},{"id":357,"type":"blueeInput","pos":[1972.1812780893092,-2938.824458391148],"size":[293.3463212467077,88],"flags":{},"order":26,"mode":0,"inputs":[{"localized_name":"text","name":"text","type":"STRING","widget":{"name":"text"},"link":null}],"outputs":[{"localized_name":"text","name":"text","type":"STRING","links":[595]}],"title":"AudioUrl","properties":{"aux_id":"WenerSantos3/ComfyUI-bluee-utils","ver":"cf6192280ac09efacd375ee47155f40d5362692c","Node name for S&R":"blueeInput"},"widgets_values":["https://d1q70pf5vjeyhc.cloudfront.net/media/ad9df18e32284c5f92ad89608854e5ec/audios/1761316963943985860_QX665455.ogg"],"color":"#233","bgcolor":"#355"},{"id":281,"type":"ImageResizeKJv2","pos":[878.8921293850445,-1896.5287394877607],"size":[270,336],"flags":{},"order":47,"mode":0,"inputs":[{"localized_name":"image","name":"image","type":"IMAGE","link":602},{"localized_name":"mask","name":"mask","shape":7,"type":"MASK","link":null},{"localized_name":"width","name":"width","type":"INT","widget":{"name":"width"},"link":494},{"localized_name":"height","name":"height","type":"INT","widget":{"name":"height"},"link":495},{"localized_name":"upscale_method","name":"upscale_method","type":"COMBO","widget":{"name":"upscale_method"},"link":null},{"localized_name":"keep_proportion","name":"keep_proportion","type":"COMBO","widget":{"name":"keep_proportion"},"link":null},{"localized_name":"pad_color","name":"pad_color","type":"STRING","widget":{"name":"pad_color"},"link":null},{"localized_name":"crop_position","name":"crop_position","type":"COMBO","widget":{"name":"crop_position"},"link":null},{"localized_name":"divisible_by","name":"divisible_by","type":"INT","widget":{"name":"divisible_by"},"link":null},{"localized_name":"device","name":"device","shape":7,"type":"COMBO","widget":{"name":"device"},"link":null}],"outputs":[{"localized_name":"IMAGE","name":"IMAGE","type":"IMAGE","links":[538]},{"localized_name":"width","name":"width","type":"INT","links":[]},{"localized_name":"height","name":"height","type":"INT","links":[]},{"localized_name":"mask","name":"mask","type":"MASK","links":null}],"properties":{"cnr_id":"comfyui-kjnodes","ver":"f7eb33abc80a2aded1b46dff0dd14d07856a7d50","Node name for S&R":"ImageResizeKJv2","ue_properties":{"widget_ue_connectable":{"width":true,"height":true},"version":"7.1","input_ue_unconnectable":{}}},"widgets_values":[832,480,"lanczos","crop","0, 0, 0","center",16,"cpu"],"color":"#223","bgcolor":"#335"},{"id":254,"type":"GetNode","pos":[3217.9006792935907,-2841.6801310263836],"size":[210,60],"flags":{"collapsed":true},"order":27,"mode":0,"inputs":[],"outputs":[{"name":"AUDIO","type":"AUDIO","links":[661]}],"title":"Get_input_audio","properties":{"ue_properties":{"widget_ue_connectable":{},"version":"7.1","input_ue_unconnectable":{}}},"widgets_values":["input_audio"],"color":"#223","bgcolor":"#335"},{"id":381,"type":"GetNode","pos":[3373.9593810866572,-2842.130936912162],"size":[210,58],"flags":{"collapsed":true},"order":28,"mode":0,"inputs":[],"outputs":[{"name":"STRING","type":"STRING","links":[660]}],"title":"Get_SetNameFile","properties":{"ue_properties":{"widget_ue_connectable":{},"version":"7.1","input_ue_unconnectable":{}}},"widgets_values":["SetNameFile"],"color":"#223","bgcolor":"#335"},{"id":194,"type":"MultiTalkWav2VecEmbeds","pos":[1013.9669211469804,-1218.9166005934944],"size":[291.08203125,278],"flags":{},"order":55,"mode":0,"inputs":[{"localized_name":"wav2vec_model","name":"wav2vec_model","type":"WAV2VECMODEL","link":334},{"localized_name":"audio_1","name":"audio_1","type":"AUDIO","link":544},{"localized_name":"audio_2","name":"audio_2","shape":7,"type":"AUDIO","link":null},{"localized_name":"audio_3","name":"audio_3","shape":7,"type":"AUDIO","link":null},{"localized_name":"audio_4","name":"audio_4","shape":7,"type":"AUDIO","link":null},{"localized_name":"ref_target_masks","name":"ref_target_masks","shape":7,"type":"MASK","link":null},{"localized_name":"normalize_loudness","name":"normalize_loudness","type":"BOOLEAN","widget":{"name":"normalize_loudness"},"link":null},{"localized_name":"num_frames","name":"num_frames","type":"INT","widget":{"name":"num_frames"},"link":529},{"localized_name":"fps","name":"fps","type":"FLOAT","widget":{"name":"fps"},"link":null},{"localized_name":"audio_scale","name":"audio_scale","type":"FLOAT","widget":{"name":"audio_scale"},"link":null},{"localized_name":"audio_cfg_scale","name":"audio_cfg_scale","type":"FLOAT","widget":{"name":"audio_cfg_scale"},"link":null},{"localized_name":"multi_audio_type","name":"multi_audio_type","type":"COMBO","widget":{"name":"multi_audio_type"},"link":null}],"outputs":[{"localized_name":"multitalk_embeds","name":"multitalk_embeds","type":"MULTITALK_EMBEDS","links":[357]},{"localized_name":"audio","name":"audio","type":"AUDIO","links":[609]},{"localized_name":"num_frames","name":"num_frames","type":"INT","links":[519]}],"properties":{"cnr_id":"ComfyUI-WanVideoWrapper","ver":"3d7801cee4c8e3106078dd9b9f146caee95069ba","Node name for S&R":"MultiTalkWav2VecEmbeds","ue_properties":{"widget_ue_connectable":{"num_frames":true},"version":"7.1","input_ue_unconnectable":{}}},"widgets_values":[true,400,25,1,1,"para"],"color":"#233","bgcolor":"#355"},{"id":400,"type":"BlueeCombineImagesAudioH264","pos":[3218.5007483947184,-2806.002271365406],"size":[388.9849609375,174],"flags":{},"order":62,"mode":0,"inputs":[{"localized_name":"images","name":"images","type":"IMAGE","link":662},{"localized_name":"audio","name":"audio","shape":7,"type":"AUDIO","link":661},{"localized_name":"frame_rate","name":"frame_rate","type":"INT","widget":{"name":"frame_rate"},"link":null},{"localized_name":"filename_prefix","name":"filename_prefix","type":"STRING","widget":{"name":"filename_prefix"},"link":660},{"localized_name":"save_output","name":"save_output","type":"BOOLEAN","widget":{"name":"save_output"},"link":null},{"localized_name":"crf","name":"crf","type":"INT","widget":{"name":"crf"},"link":null},{"localized_name":"preset","name":"preset","type":"COMBO","widget":{"name":"preset"},"link":null}],"outputs":[{"localized_name":"path","name":"path","type":"STRING","links":[664]}],"properties":{"aux_id":"WenerSantos3/ComfyUI-bluee-utils","ver":"cf6192280ac09efacd375ee47155f40d5362692c","Node name for S&R":"BlueeCombineImagesAudioH264"},"widgets_values":[25,"BlueeVideo",true,19,"medium"],"color":"#2a363b","bgcolor":"#3f5159"},{"id":406,"type":"BlueeUtilsDelete","pos":[4300.671948501156,-2859.7494021138114],"size":[270,58],"flags":{"collapsed":false},"order":65,"mode":0,"inputs":[{"localized_name":"trigger","name":"trigger","type":"*","link":674},{"localized_name":"path","name":"path","type":"STRING","widget":{"name":"path"},"link":672}],"outputs":[],"properties":{"aux_id":"WenerSantos3/ComfyUI-bluee-utils","ver":"cf6192280ac09efacd375ee47155f40d5362692c","Node name for S&R":"BlueeUtilsDelete"},"widgets_values":[""]},{"id":375,"type":"GetNode","pos":[4309.9210911787995,-2738.6239739716757],"size":[210,50],"flags":{"collapsed":true},"order":29,"mode":0,"inputs":[],"outputs":[{"name":"STRING","type":"STRING","links":[671]}],"title":"Get_AudioPath","properties":{"ue_properties":{"widget_ue_connectable":{},"version":"7.1","input_ue_unconnectable":{}}},"widgets_values":["AudioPath"],"color":"#223","bgcolor":"#335"},{"id":405,"type":"BlueeUtilsDelete","pos":[4309.3626791167635,-2696.425529894285],"size":[270,58],"flags":{"collapsed":false},"order":64,"mode":0,"inputs":[{"localized_name":"trigger","name":"trigger","type":"*","link":673},{"localized_name":"path","name":"path","type":"STRING","widget":{"name":"path"},"link":671}],"outputs":[],"properties":{"aux_id":"WenerSantos3/ComfyUI-bluee-utils","ver":"cf6192280ac09efacd375ee47155f40d5362692c","Node name for S&R":"BlueeUtilsDelete"},"widgets_values":[""]},{"id":376,"type":"GetNode","pos":[4301.105648673934,-2898.7713735289008],"size":[210,50],"flags":{"collapsed":true},"order":30,"mode":0,"inputs":[],"outputs":[{"name":"STRING","type":"STRING","links":[672]}],"title":"Get_ImagePath","properties":{"ue_properties":{"widget_ue_connectable":{},"version":"7.1","input_ue_unconnectable":{}}},"widgets_values":["ImagePath"],"color":"#223","bgcolor":"#335"},{"id":378,"type":"UploadFileS3","pos":[3647.7539158406807,-2821.0751034327577],"size":[270,106],"flags":{},"order":63,"mode":0,"inputs":[{"localized_name":"local_path","name":"local_path","type":"STRING","widget":{"name":"local_path"},"link":664},{"localized_name":"s3_folder","name":"s3_folder","type":"STRING","widget":{"name":"s3_folder"},"link":null},{"localized_name":"delete_local","name":"delete_local","type":"COMBO","widget":{"name":"delete_local"},"link":null}],"outputs":[{"localized_name":"s3_paths","name":"s3_paths","type":"STRING","links":[673,674,675]}],"properties":{"cnr_id":"comfys3","ver":"1.0.1","Node name for S&R":"UploadFileS3"},"widgets_values":["input/example.png","bluee-talk/videos","true"],"color":"#2a363b","bgcolor":"#3f5159"},{"id":128,"type":"WanVideoSampler","pos":[2772.990085043837,-1899.4169396246712],"size":[315,999],"flags":{},"order":60,"mode":0,"inputs":[{"localized_name":"model","name":"model","type":"WANVIDEOMODEL","link":464},{"localized_name":"image_embeds","name":"image_embeds","type":"WANVIDIMAGE_EMBEDS","link":413},{"localized_name":"text_embeds","name":"text_embeds","shape":7,"type":"WANVIDEOTEXTEMBEDS","link":437},{"localized_name":"samples","name":"samples","shape":7,"type":"LATENT","link":null},{"localized_name":"feta_args","name":"feta_args","shape":7,"type":"FETAARGS","link":null},{"localized_name":"context_options","name":"context_options","shape":7,"type":"WANVIDCONTEXT","link":null},{"localized_name":"cache_args","name":"cache_args","shape":7,"type":"CACHEARGS","link":552},{"localized_name":"flowedit_args","name":"flowedit_args","shape":7,"type":"FLOWEDITARGS","link":null},{"localized_name":"slg_args","name":"slg_args","shape":7,"type":"SLGARGS","link":null},{"localized_name":"loop_args","name":"loop_args","shape":7,"type":"LOOPARGS","link":null},{"localized_name":"experimental_args","name":"experimental_args","shape":7,"type":"EXPERIMENTALARGS","link":null},{"localized_name":"sigmas","name":"sigmas","shape":7,"type":"SIGMAS","link":null},{"localized_name":"unianimate_poses","name":"unianimate_poses","shape":7,"type":"UNIANIMATE_POSE","link":null},{"localized_name":"fantasytalking_embeds","name":"fantasytalking_embeds","shape":7,"type":"FANTASYTALKING_EMBEDS","link":null},{"localized_name":"uni3c_embeds","name":"uni3c_embeds","shape":7,"type":"UNI3C_EMBEDS","link":null},{"localized_name":"multitalk_embeds","name":"multitalk_embeds","shape":7,"type":"MULTITALK_EMBEDS","link":357},{"localized_name":"freeinit_args","name":"freeinit_args","shape":7,"type":"FREEINITARGS","link":null},{"localized_name":"steps","name":"steps","type":"INT","widget":{"name":"steps"},"link":null},{"localized_name":"cfg","name":"cfg","type":"FLOAT","widget":{"name":"cfg"},"link":null},{"localized_name":"shift","name":"shift","type":"FLOAT","widget":{"name":"shift"},"link":null},{"localized_name":"seed","name":"seed","type":"INT","widget":{"name":"seed"},"link":null},{"localized_name":"force_offload","name":"force_offload","type":"BOOLEAN","widget":{"name":"force_offload"},"link":null},{"localized_name":"scheduler","name":"scheduler","type":"COMBO","widget":{"name":"scheduler"},"link":null},{"localized_name":"riflex_freq_index","name":"riflex_freq_index","type":"INT","widget":{"name":"riflex_freq_index"},"link":null},{"localized_name":"denoise_strength","name":"denoise_strength","shape":7,"type":"FLOAT","widget":{"name":"denoise_strength"},"link":null},{"localized_name":"batched_cfg","name":"batched_cfg","shape":7,"type":"BOOLEAN","widget":{"name":"batched_cfg"},"link":null},{"localized_name":"rope_function","name":"rope_function","shape":7,"type":"COMBO","widget":{"name":"rope_function"},"link":null},{"localized_name":"start_step","name":"start_step","shape":7,"type":"INT","widget":{"name":"start_step"},"link":null},{"localized_name":"end_step","name":"end_step","shape":7,"type":"INT","widget":{"name":"end_step"},"link":null},{"localized_name":"add_noise_to_samples","name":"add_noise_to_samples","shape":7,"type":"BOOLEAN","widget":{"name":"add_noise_to_samples"},"link":null}],"outputs":[{"localized_name":"samples","name":"samples","type":"LATENT","slot_index":0,"links":[550]},{"localized_name":"denoised_samples","name":"denoised_samples","type":"LATENT","links":null}],"properties":{"cnr_id":"ComfyUI-WanVideoWrapper","ver":"c3ee35f3ece76e38099dc516182d69b406e16772","Node name for S&R":"WanVideoSampler","ue_properties":{"widget_ue_connectable":{},"version":"7.1","input_ue_unconnectable":{}}},"widgets_values":[6,1.0000000000000002,7,2,"fixed",true,"dpm++_sde",0,1,false,"comfy",0,-1,true],"color":"#332922","bgcolor":"#593930"},{"id":408,"type":"PreviewAny","pos":[3996.833042830118,-2953.2542479180834],"size":[210,88],"flags":{},"order":66,"mode":0,"inputs":[{"localized_name":"source","name":"source","type":"*","link":675}],"outputs":[],"properties":{"cnr_id":"comfy-core","ver":"0.3.67","Node name for S&R":"PreviewAny"},"widgets_values":[]},{"id":354,"type":"blueeInput","pos":[1964.8546084602065,-3082.8541480412296],"size":[300.52493423971737,93.34632124670816],"flags":{},"order":31,"mode":0,"inputs":[{"localized_name":"text","name":"text","type":"STRING","widget":{"name":"text"},"link":null}],"outputs":[{"localized_name":"text","name":"text","type":"STRING","links":[592]}],"title":"ImageUrl","properties":{"aux_id":"WenerSantos3/ComfyUI-bluee-utils","ver":"cf6192280ac09efacd375ee47155f40d5362692c","Node name for S&R":"blueeInput"},"widgets_values":["https://d1q70pf5vjeyhc.cloudfront.net/media/ad9df18e32284c5f92ad89608854e5ec/images/1761856047691388117_wySdb62Z.png"],"color":"#233","bgcolor":"#355"}],"links":[[334,137,0,194,0,"WAV2VECMODEL"],[349,138,0,122,2,"WANVIDLORA"],[355,120,0,122,6,"MULTITALKMODEL"],[357,194,0,128,15,"MULTITALK_EMBEDS"],[362,134,0,122,1,"BLOCKSWAPARGS"],[413,192,0,128,1,"WANVIDIMAGE_EMBEDS"],[433,237,0,192,2,"WANVIDIMAGE_CLIPEMBEDS"],[436,129,0,240,0,"*"],[437,241,0,128,2,"WANVIDEOTEXTEMBEDS"],[440,244,0,192,0,"WANVAE"],[441,245,0,247,0,"*"],[442,246,0,248,0,"*"],[463,122,0,260,0,"*"],[464,261,0,128,0,"WANVIDEOMODEL"],[466,238,0,264,0,"*"],[467,265,0,237,0,"CLIP_VISION"],[472,270,0,271,0,"*"],[494,283,0,281,2,"INT"],[495,282,0,281,3,"INT"],[516,291,1,192,3,"INT"],[517,291,2,192,4,"INT"],[519,194,2,294,0,"*"],[529,272,0,194,7,"INT"],[538,281,0,291,0,"IMAGE"],[539,291,0,237,1,"IMAGE"],[540,291,0,192,1,"IMAGE"],[543,301,0,302,0,"MELROFORMERMODEL"],[544,302,0,194,1,"AUDIO"],[550,128,0,309,0,"LATENT"],[552,311,0,128,6,"CACHEARGS"],[587,350,0,351,0,"*"],[592,354,0,355,0,"STRING"],[593,355,0,339,0,"STRING"],[595,357,0,358,0,"STRING"],[596,358,0,342,0,"STRING"],[598,360,0,350,0,"STRING"],[599,362,0,348,0,"STRING"],[600,361,0,346,0,"STRING"],[602,364,0,281,0,"IMAGE"],[603,364,0,365,0,"IMAGE"],[604,366,0,241,3,"STRING"],[605,367,0,241,4,"STRING"],[609,194,1,370,0,"AUDIO"],[612,373,0,302,1,"AUDIO"],[613,373,0,253,0,"AUDIO"],[639,352,0,364,0,"STRING"],[641,369,0,373,0,"STRING"],[660,381,0,400,3,"STRING"],[661,254,0,400,1,"AUDIO"],[662,309,0,400,0,"IMAGE"],[664,400,0,378,0,"STRING"],[671,375,0,405,1,"STRING"],[672,376,0,406,1,"STRING"],[673,378,0,405,0,"*"],[674,378,0,406,0,"*"],[675,378,0,408,0,"*"]],"groups":[{"id":1,"title":"Models","bounding":[468.59401964612374,-3166.5750928767975,1421.3189154644078,1098.5205518118769],"color":"#88A","font_size":24,"flags":{}},{"id":4,"title":"Audio","bounding":[479.2722748292025,-1529.4639414894066,1782.2769775390625,833.420166015625],"color":"#a1309b","font_size":24,"flags":{}},{"id":5,"title":"Input image","bounding":[471.458072886824,-2044.41552734375,1787.0530379791444,493.8471999240253],"color":"#3f789e","font_size":24,"flags":{}},{"id":6,"title":"Inputs","bounding":[1933.3940319644605,-3163.5906250343455,1232.1838305590516,1096.4230409689367],"color":"#3f789e","font_size":24,"flags":{}},{"id":7,"title":"Generate","bounding":[2272.239373018535,-2038.8588844047674,900.9416195471194,1349.0909713808635],"color":"#444","font_size":24,"flags":{}},{"id":8,"title":"FinalRender concat","bounding":[3192.040130277127,-3163.509953254483,1452.9533706780026,2457.1300074915753],"color":"#3f789e","font_size":24,"flags":{}}],"config":{},"extra":{"ds":{"scale":0.8724690910661576,"offset":[-2236.466708379936,2931.8364892443346]},"frontendVersion":"1.26.13","node_versions":{"ComfyUI-WanVideoWrapper":"0a11c67a0c0062b534178920a0d6dcaa75e7b5fe","comfy-core":"0.3.43","audio-separation-nodes-comfyui":"31a4567726e035097cc2d1f767767908a6fda2ea","ComfyUI-KJNodes":"f7eb33abc80a2aded1b46dff0dd14d07856a7d50","comfyui-videohelpersuite":"a7ce59e381934733bfae03b1be029756d6ce936d"},"VHS_latentpreview":true,"VHS_latentpreviewrate":0,"VHS_MetadataImage":true,"VHS_KeepIntermediate":true,"ue_links":[],"links_added_by_ue":[]},"version":0.4}